abx_plugin_pip/.plugin_order
abx_plugin_pip/__init__.py
abx_plugin_pip/binaries.py
abx_plugin_pip/binproviders.py
abx_plugin_pip/config.py
abx_plugin_pip-2024.10.24.dist-info/METADATA
abx_plugin_pip-2024.10.24.dist-info/WHEEL
abx_plugin_pip-2024.10.24.dist-info/entry_points.txt
abx_plugin_pip-2024.10.24.dist-info/RECORD
